farshid/__init__.py
farshid/pirahansiah.py
pirahansiah-0.0.10.dist-info/LICENSE.txt
pirahansiah-0.0.10.dist-info/METADATA
pirahansiah-0.0.10.dist-info/WHEEL
pirahansiah-0.0.10.dist-info/top_level.txt
pirahansiah-0.0.10.dist-info/RECORD
