Metadata-Version: 2.1
Name: pirahansiah
Version: 0.0.10
Summary: Farshid PirahanSiah workshop computer vision OpenCV
Home-page: https://gitlab.com/pirahansiah/farshid
Author: Farshid PirahanSiah
Author-email: pirahansiah@gmail.com
License: UNKNOWN
Platform: UNKNOWN
Classifier: Programming Language :: Python :: 3
Classifier: License :: OSI Approved :: MIT License
Classifier: Operating System :: OS Independent
